smart_chart/__init__.py
smart_chart/config.ini
smart_chart/sqlite.db
smart_chart/bin/smartchart
smart_chart/bin/smartchart.bat
smart_chart/bin/smartcharts
smart_chart/bin/smartcharts.bat
smart_chart/common/__init__.py
smart_chart/common/connect_db.py
smart_chart/common/function.py
smart_chart/common/functions.py
smart_chart/common/jsmin.py
smart_chart/common/jsmin2.py
smart_chart/common/scheduler.py
smart_chart/common/smartvector.py
smart_chart/common/tools.py
smart_chart/common/jdbclib/__init__.py
smart_chart/common/jdbclib/bailianAI.py
smart_chart/common/jdbclib/dashAI.py
smart_chart/common/jdbclib/feishuExcel.py
smart_chart/common/jdbclib/prometheus.py
smart_chart/common/jdbclib/qiweiMsg.py
smart_chart/common/jdbclib/smtpmail.py
smart_chart/common/jdbclib/vectorPostgres.py
smart_chart/echart/__init__.py
smart_chart/echart/_db.json
smart_chart/echart/admin.py
smart_chart/echart/apps.py
smart_chart/echart/editor.py
smart_chart/echart/forms.py
smart_chart/echart/index.py
smart_chart/echart/models.py
smart_chart/echart/note.py
smart_chart/echart/urls.py
smart_chart/echart/views.py
smart_chart/echart/migrations/__init__.py
smart_chart/echart/static/ace/ace.js
smart_chart/echart/static/ace/ext-beautify.js
smart_chart/echart/static/ace/ext-elastic_tabstops_lite.js
smart_chart/echart/static/ace/ext-emmet.js
smart_chart/echart/static/ace/ext-error_marker.js
smart_chart/echart/static/ace/ext-keybinding_menu.js
smart_chart/echart/static/ace/ext-language_tools.js
smart_chart/echart/static/ace/ext-linking.js
smart_chart/echart/static/ace/ext-modelist.js
smart_chart/echart/static/ace/ext-options.js
smart_chart/echart/static/ace/ext-rtl.js
smart_chart/echart/static/ace/ext-searchbox.js
smart_chart/echart/static/ace/ext-settings_menu.js
smart_chart/echart/static/ace/ext-spellcheck.js
smart_chart/echart/static/ace/ext-split.js
smart_chart/echart/static/ace/ext-static_highlight.js
smart_chart/echart/static/ace/ext-statusbar.js
smart_chart/echart/static/ace/ext-textarea.js
smartai-7.5.4.dist-info/METADATA
smartai-7.5.4.dist-info/WHEEL
smartai-7.5.4.dist-info/top_level.txt
smartai-7.5.4.dist-info/RECORD
