Metadata-Version: 2.1
Name: smartai
Version: 7.5.4
Summary: 面向开发的数据应用开发平台
Home-page: https://www.smartchart.cn/
Author: JohnYan
Author-email: 84345999@qq.com
License: UNKNOWN
Download-URL: https://www.smartchart.cn/
Platform: UNKNOWN
Classifier: Development Status :: 5 - Production/Stable
Classifier: Environment :: Console
Classifier: Environment :: Web Environment
Classifier: Intended Audience :: Developers
Classifier: Intended Audience :: System Administrators
Classifier: License :: OSI Approved :: Apache Software License
Classifier: Programming Language :: Python :: 3.9
Requires-Python: >=3.6
Requires-Dist: Django (<5.0,>=2.1)
Requires-Dist: PyMySQL
Requires-Dist: requests
Requires-Dist: smartdb
